woocommerceaio/__init__.py
woocommerceaio/api.py
woocommerceaio/oauth.py
woocommerceaio/py.typed
woocommerceaio-1.1.4.dist-info/LICENSE
woocommerceaio-1.1.4.dist-info/METADATA
woocommerceaio-1.1.4.dist-info/WHEEL
woocommerceaio-1.1.4.dist-info/top_level.txt
woocommerceaio-1.1.4.dist-info/RECORD
